gzip_static/__init__.py
gzip_static/extensions.txt
gzip_static-0.1.0.dist-info/LICENSE
gzip_static-0.1.0.dist-info/METADATA
gzip_static-0.1.0.dist-info/WHEEL
gzip_static-0.1.0.dist-info/entry_points.txt
gzip_static-0.1.0.dist-info/top_level.txt
gzip_static-0.1.0.dist-info/RECORD
