Metadata-Version: 2.1
Name: gzip-static
Version: 0.1.0
Summary: Compress your static website with gzip for faster serving with NGiNX's gzip_static on.
Home-page: https://github.com/rhpvorderman/gzip_static
Author: Ruben Vorderman
Author-email: rubenvorderman@gmail.com
License: GPL-3.0-or-later
Keywords: static html precompression gzip checksum
Platform: UNKNOWN
Classifier: Programming Language :: Python :: 3 :: Only
Classifier: Programming Language :: Python :: 3
Classifier: Programming Language :: Python :: 3.6
Classifier: Programming Language :: Python :: 3.7
Classifier: Programming Language :: Python :: 3.8
Classifier: Programming Language :: Python :: 3.9
Classifier: Programming Language :: Python :: 3.10
Classifier: License :: OSI Approved :: GNU General Public License v3 or later (GPLv3+)
Requires-Python: >=3.6
License-File: LICENSE
Provides-Extra: full
Requires-Dist: zopfli ; extra == 'full'
Requires-Dist: xxhash (>=2.0.0) ; extra == 'full'
Requires-Dist: isal ; extra == 'full'
Provides-Extra: performance
Requires-Dist: xxhash (>=2.0.0) ; extra == 'performance'
Requires-Dist: isal ; extra == 'performance'
Provides-Extra: zopfli
Requires-Dist: zopfli ; extra == 'zopfli'
